{
  "features": {
    "0": {
      "col": 0,
      "row": 0
    },
    "1": {
      "col": 1,
      "row": 0
    },
    "2": {
      "col": 1,
      "row": 0
    },
    "3": {
      "col": 21,
      "row": 13
    },
    "4": {
      "col": 4,
      "row": 2
    },
    "5": {
      "col": 5,
      "row": 2
    },
    "6": {
      "col": 22,
      "row": 0
    },
    "7": {
      "col": 25,
      "row": 0
    },
    "8": {
      "col": 29,
      "row": 59
    },
    "9": {
      "col": 5,
      "row": 60
    },
    "10": {
      "col": 26,
      "row": 59
    },
    "11": {
      "col": 23,
      "row": 59
    },
    "12": {
      "col": 5,
      "row": 59
    },
    "13": {
      "col": 8,
      "row": 59
    },
    "14": {
      "col": 11,
      "row": 59
    },
    "15": {
      "col": 20,
      "row": 61
    },
    "16": {
      "col": 12,
      "row": 1
    },
    "17": {
      "col": 9,
      "row": 1
    },
    "18": {
      "col": 9,
      "row": 1
    },
    "19": {
      "col": 9,
      "row": 1
    },
    "20": {
      "col": 15,
      "row": 1
    },
    "21": {
      "col": 18,
      "row": 1
    },
    "22": {
      "col": 6,
      "row": 1
    },
    "23": {
      "col": 6,
      "row": 1
    },
    "24": {
      "col": 0,
      "row": 1
    },
    "25": {
      "col": 0,
      "row": 1
    },
    "26": {
      "col": 0,
      "row": 1
    },
    "27": {
      "col": 0,
      "row": 1
    },
    "28": {
      "col": 3,
      "row": 1
    },
    "29": {
      "col": 3,
      "row": 1
    },
    "30": {
      "col": 3,
      "row": 1
    },
    "31": {
      "col": 3,
      "row": 1
    },
    "32": {
      "col": 3,
      "row": 2
    },
    "33": {
      "col": 2,
      "row": 59
    },
    "48": {
      "col": 4,
      "row": 0
    },
    "49": {
      "col": 28,
      "row": 0
    },
    "50": {
      "col": 13,
      "row": 0
    },
    "51": {
      "col": 7,
      "row": 0
    },
    "52": {
      "col": 16,
      "row": 0
    },
    "53": {
      "col": 7,
      "row": 0
    },
    "54": {
      "col": 16,
      "row": 0
    },
    "55": {
      "col": 10,
      "row": 0
    },
    "56": {
      "col": 4,
      "row": 0
    },
    "57": {
      "col": 4,
      "row": 0
    },
    "58": {
      "col": 4,
      "row": 0
    },
    "59": {
      "col": 4,
      "row": 0
    },
    "60": {
      "col": 19,
      "row": 0
    },
    "61": {
      "col": 19,
      "row": 0
    },
    "62": {
      "col": 19,
      "row": 0
    },
    "63": {
      "col": 19,
      "row": 0
    },
    "64": {
      "col": 26,
      "row": 3
    },
    "65": {
      "col": 21,
      "row": 1
    },
    "66": {
      "col": 21,
      "row": 1
    },
    "67": {
      "col": 21,
      "row": 1
    },
    "68": {
      "col": 21,
      "row": 1
    },
    "69": {
      "col": 21,
      "row": 1
    },
    "70": {
      "col": 21,
      "row": 1
    },
    "71": {
      "col": 24,
      "row": 1
    },
    "72": {
      "col": 27,
      "row": 1
    },
    "73": {
      "col": 30,
      "row": 1
    },
    "74": {
      "col": 7,
      "row": 2
    },
    "75": {
      "col": 8,
      "row": 2
    },
    "76": {
      "col": 9,
      "row": 2
    },
    "77": {
      "col": 10,
      "row": 2
    },
    "78": {
      "col": 11,
      "row": 2
    },
    "79": {
      "col": 12,
      "row": 2
    },
    "80": {
      "col": 13,
      "row": 2
    },
    "81": {
      "col": 14,
      "row": 2
    },
    "82": {
      "col": 15,
      "row": 2
    },
    "83": {
      "col": 0,
      "row": 3
    },
    "84": {
      "col": 3,
      "row": 3
    },
    "85": {
      "col": 29,
      "row": 54
    },
    "86": {
      "col": 26,
      "row": 54
    },
    "87": {
      "col": 23,
      "row": 61
    },
    "88": {
      "col": 20,
      "row": 59
    },
    "89": {
      "col": 14,
      "row": 59
    },
    "90": {
      "col": 18,
      "row": 1
    },
    "91": {
      "col": 1,
      "row": 0
    },
    "92": {
      "col": 14,
      "row": 60
    },
    "93": {
      "col": 11,
      "row": 60
    },
    "94": {
      "col": 8,
      "row": 60
    },
    "95": {
      "col": 17,
      "row": 60
    },
    "96": {
      "col": 12,
      "row": 62
    },
    "97": {
      "col": 14,
      "row": 61
    },
    "98": {
      "col": 17,
      "row": 61
    },
    "99": {
      "col": 0,
      "row": 62
    },
    "100": {
      "col": 20,
      "row": 60
    },
    "101": {
      "col": 23,
      "row": 60
    },
    "102": {
      "col": 2,
      "row": 61
    },
    "103": {
      "col": 2,
      "row": 59
    },
    "112": {
      "col": 11,
      "row": 61
    },
    "113": {
      "col": 26,
      "row": 61
    },
    "114": {
      "col": 3,
      "row": 62
    },
    "115": {
      "col": 26,
      "row": 2
    },
    "128": {
      "col": 29,
      "row": 60
    },
    "129": {
      "col": 29,
      "row": 61
    },
    "130": {
      "col": 17,
      "row": 59
    },
    "131": {
      "col": 5,
      "row": 61
    },
    "132": {
      "col": 8,
      "row": 61
    },
    "133": {
      "col": 26,
      "row": 60
    },
    "134": {
      "col": 29,
      "row": 61
    },
    "135": {
      "col": 2,
      "row": 60
    },
    "136": {
      "col": 6,
      "row": 62
    },
    "137": {
      "col": 9,
      "row": 62
    },
    "140": {
      "col": 7,
      "row": 2
    },
    "141": {
      "col": 8,
      "row": 2
    },
    "142": {
      "col": 9,
      "row": 2
    },
    "143": {
      "col": 10,
      "row": 2
    },
    "144": {
      "col": 11,
      "row": 2
    },
    "145": {
      "col": 12,
      "row": 2
    },
    "146": {
      "col": 13,
      "row": 2
    },
    "147": {
      "col": 14,
      "row": 2
    },
    "149": {
      "col": 0,
      "row": 65
    },
    "150": {
      "col": 15,
      "row": 62
    },
    "151": {
      "col": 22,
      "row": 62
    },
    "153": {
      "col": 20,
      "row": 62
    }
  },
  "monsters": {
    "0": {
      "col": 0,
      "row": 18
    },
    "1": {
      "col": 0,
      "row": 42
    },
    "2": {
      "col": 2,
      "row": 39
    },
    "3": {
      "col": 0,
      "row": 55
    },
    "4": {
      "col": 1,
      "row": 55
    },
    "5": {
      "col": 2,
      "row": 55
    },
    "6": {
      "col": 3,
      "row": 55
    },
    "7": {
      "col": 26,
      "row": 29
    },
    "8": {
      "col": 1,
      "row": 42
    },
    "9": {
      "col": 2,
      "row": 42
    },
    "10": {
      "col": 3,
      "row": 42
    },
    "11": {
      "col": 4,
      "row": 42
    },
    "12": {
      "col": 5,
      "row": 42
    },
    "13": {
      "col": 6,
      "row": 42
    },
    "14": {
      "col": 7,
      "row": 42
    },
    "15": {
      "col": 8,
      "row": 42
    },
    "16": {
      "col": 9,
      "row": 42
    },
    "17": {
      "col": 10,
      "row": 42
    },
    "18": {
      "col": 11,
      "row": 42
    },
    "19": {
      "col": 0,
      "row": 48
    },
    "20": {
      "col": 31,
      "row": 40
    },
    "21": {
      "col": 5,
      "row": 34
    },
    "22": {
      "col": 1,
      "row": 48
    },
    "23": {
      "col": 2,
      "row": 48
    },
    "24": {
      "col": 21,
      "row": 37
    },
    "25": {
      "col": 3,
      "row": 40
    },
    "26": {
      "col": 4,
      "row": 40
    },
    "27": {
      "col": 5,
      "row": 44
    },
    "28": {
      "col": 4,
      "row": 34
    },
    "29": {
      "col": 25,
      "row": 40
    },
    "30": {
      "col": 26,
      "row": 40
    },
    "31": {
      "col": 29,
      "row": 44
    },
    "32": {
      "col": 27,
      "row": 38
    },
    "33": {
      "col": 6,
      "row": 34
    },
    "34": {
      "col": 4,
      "row": 48
    },
    "35": {
      "col": 27,
      "row": 29
    },
    "36": {
      "col": 7,
      "row": 37
    },
    "37": {
      "col": 15,
      "row": 37
    },
    "38": {
      "col": 4,
      "row": 55
    },
    "39": {
      "col": 3,
      "row": 48
    },
    "40": {
      "col": 6,
      "row": 29
    },
    "41": {
      "col": 5,
      "row": 40
    },
    "42": {
      "col": 22,
      "row": 37
    },
    "43": {
      "col": 12,
      "row": 42
    },
    "44": {
      "col": 13,
      "row": 42
    },
    "45": {
      "col": 14,
      "row": 42
    },
    "46": {
      "col": 15,
      "row": 42
    },
    "47": {
      "col": 7,
      "row": 29
    },
    "48": {
      "col": 10,
      "row": 40
    },
    "49": {
      "col": 8,
      "row": 37
    },
    "50": {
      "col": 8,
      "row": 34
    },
    "51": {
      "col": 8,
      "row": 32
    },
    "52": {
      "col": 7,
      "row": 45
    },
    "53": {
      "col": 28,
      "row": 29
    },
    "54": {
      "col": 5,
      "row": 55
    },
    "55": {
      "col": 29,
      "row": 29
    },
    "56": {
      "col": 7,
      "row": 34
    },
    "57": {
      "col": 5,
      "row": 48
    },
    "58": {
      "col": 30,
      "row": 44
    },
    "59": {
      "col": 9,
      "row": 34
    },
    "60": {
      "col": 29,
      "row": 34
    },
    "61": {
      "col": 6,
      "row": 55
    },
    "62": {
      "col": 3,
      "row": 39
    },
    "63": {
      "col": 16,
      "row": 42
    },
    "64": {
      "col": 11,
      "row": 40
    },
    "65": {
      "col": 25,
      "row": 31
    },
    "66": {
      "col": 13,
      "row": 40
    },
    "67": {
      "col": 23,
      "row": 37
    },
    "68": {
      "col": 7,
      "row": 55
    },
    "69": {
      "col": 29,
      "row": 40
    },
    "70": {
      "col": 8,
      "row": 55
    },
    "71": {
      "col": 8,
      "row": 41
    },
    "72": {
      "col": 8,
      "row": 29
    },
    "73": {
      "col": 12,
      "row": 40
    },
    "74": {
      "col": 19,
      "row": 39
    },
    "75": {
      "col": 9,
      "row": 37
    },
    "76": {
      "col": 0,
      "row": 41
    },
    "77": {
      "col": 24,
      "row": 37
    },
    "78": {
      "col": 31,
      "row": 44
    },
    "79": {
      "col": 0,
      "row": 45
    },
    "80": {
      "col": 28,
      "row": 38
    },
    "81": {
      "col": 9,
      "row": 55
    },
    "82": {
      "col": 10,
      "row": 34
    },
    "83": {
      "col": 17,
      "row": 42
    },
    "84": {
      "col": 14,
      "row": 40
    },
    "85": {
      "col": 0,
      "row": 29
    },
    "86": {
      "col": 6,
      "row": 44
    },
    "87": {
      "col": 10,
      "row": 55
    },
    "88": {
      "col": 11,
      "row": 55
    },
    "89": {
      "col": 1,
      "row": 45
    },
    "90": {
      "col": 11,
      "row": 34
    },
    "91": {
      "col": 9,
      "row": 44
    },
    "92": {
      "col": 6,
      "row": 48
    },
    "93": {
      "col": 15,
      "row": 42
    },
    "94": {
      "col": 9,
      "row": 41
    },
    "95": {
      "col": 12,
      "row": 55
    },
    "96": {
      "col": 13,
      "row": 55
    },
    "97": {
      "col": 18,
      "row": 42
    },
    "98": {
      "col": 14,
      "row": 55
    },
    "99": {
      "col": 15,
      "row": 40
    },
    "100": {
      "col": 26,
      "row": 31
    },
    "101": {
      "col": 16,
      "row": 40
    },
    "102": {
      "col": 27,
      "row": 40
    },
    "103": {
      "col": 6,
      "row": 40
    },
    "104": {
      "col": 29,
      "row": 38
    },
    "105": {
      "col": 2,
      "row": 45
    },
    "106": {
      "col": 12,
      "row": 34
    },
    "107": {
      "col": 7,
      "row": 48
    },
    "108": {
      "col": 9,
      "row": 29
    },
    "109": {
      "col": 14,
      "row": 42
    },
    "110": {
      "col": 12,
      "row": 42
    },
    "111": {
      "col": 8,
      "row": 48
    },
    "112": {
      "col": 9,
      "row": 48
    },
    "113": {
      "col": 1,
      "row": 41
    },
    "114": {
      "col": 16,
      "row": 37
    },
    "115": {
      "col": 15,
      "row": 55
    },
    "116": {
      "col": 23,
      "row": 42
    },
    "117": {
      "col": 1,
      "row": 29
    },
    "118": {
      "col": 14,
      "row": 41
    },
    "119": {
      "col": 13,
      "row": 34
    },
    "120": {
      "col": 16,
      "row": 55
    },
    "121": {
      "col": 14,
      "row": 34
    },
    "122": {
      "col": 21,
      "row": 39
    },
    "123": {
      "col": 12,
      "row": 45
    },
    "124": {
      "col": 10,
      "row": 48
    },
    "125": {
      "col": 11,
      "row": 48
    },
    "126": {
      "col": 15,
      "row": 41
    },
    "127": {
      "col": 30,
      "row": 34
    },
    "128": {
      "col": 17,
      "row": 32
    },
    "129": {
      "col": 30,
      "row": 38
    },
    "130": {
      "col": 10,
      "row": 41
    },
    "131": {
      "col": 17,
      "row": 40
    },
    "132": {
      "col": 7,
      "row": 40
    },
    "133": {
      "col": 27,
      "row": 31
    },
    "134": {
      "col": 15,
      "row": 34
    },
    "135": {
      "col": 28,
      "row": 40
    },
    "136": {
      "col": 10,
      "row": 44
    },
    "137": {
      "col": 24,
      "row": 42
    },
    "138": {
      "col": 12,
      "row": 48
    },
    "139": {
      "col": 17,
      "row": 55
    },
    "140": {
      "col": 16,
      "row": 41
    },
    "141": {
      "col": 8,
      "row": 45
    },
    "142": {
      "col": 17,
      "row": 42
    },
    "143": {
      "col": 16,
      "row": 34
    },
    "145": {
      "col": 18,
      "row": 55
    },
    "146": {
      "col": 2,
      "row": 41
    },
    "147": {
      "col": 18,
      "row": 42
    },
    "148": {
      "col": 18,
      "row": 32
    },
    "149": {
      "col": 17,
      "row": 41
    },
    "150": {
      "col": 27,
      "row": 42
    },
    "151": {
      "col": 14,
      "row": 48
    },
    "152": {
      "col": 15,
      "row": 48
    },
    "153": {
      "col": 16,
      "row": 48
    },
    "154": {
      "col": 17,
      "row": 36
    },
    "155": {
      "col": 8,
      "row": 40
    },
    "156": {
      "col": 7,
      "row": 44
    },
    "157": {
      "col": 9,
      "row": 32
    },
    "158": {
      "col": 19,
      "row": 55
    },
    "159": {
      "col": 20,
      "row": 55
    },
    "160": {
      "col": 21,
      "row": 55
    },
    "161": {
      "col": 22,
      "row": 55
    },
    "162": {
      "col": 18,
      "row": 41
    },
    "163": {
      "col": 29,
      "row": 37
    },
    "164": {
      "col": 30,
      "row": 37
    },
    "165": {
      "col": 31,
      "row": 37
    },
    "166": {
      "col": 0,
      "row": 38
    },
    "167": {
      "col": 1,
      "row": 38
    },
    "168": {
      "col": 13,
      "row": 37
    },
    "169": {
      "col": 28,
      "row": 42
    },
    "170": {
      "col": 23,
      "row": 55
    },
    "171": {
      "col": 17,
      "row": 34
    },
    "172": {
      "col": 24,
      "row": 55
    },
    "173": {
      "col": 17,
      "row": 48
    },
    "174": {
      "col": 18,
      "row": 48
    },
    "175": {
      "col": 31,
      "row": 34
    },
    "176": {
      "col": 18,
      "row": 44
    },
    "177": {
      "col": 25,
      "row": 55
    },
    "178": {
      "col": 22,
      "row": 39
    },
    "179": {
      "col": 26,
      "row": 55
    },
    "180": {
      "col": 9,
      "row": 45
    },
    "181": {
      "col": 27,
      "row": 55
    },
    "182": {
      "col": 23,
      "row": 39
    },
    "183": {
      "col": 29,
      "row": 55
    },
    "184": {
      "col": 10,
      "row": 29
    },
    "185": {
      "col": 19,
      "row": 48
    },
    "186": {
      "col": 19,
      "row": 41
    },
    "187": {
      "col": 30,
      "row": 55
    },
    "188": {
      "col": 31,
      "row": 55
    },
    "189": {
      "col": 0,
      "row": 56
    },
    "190": {
      "col": 3,
      "row": 41
    },
    "191": {
      "col": 1,
      "row": 56
    },
    "192": {
      "col": 4,
      "row": 41
    },
    "193": {
      "col": 2,
      "row": 38
    },
    "194": {
      "col": 19,
      "row": 32
    },
    "195": {
      "col": 2,
      "row": 29
    },
    "196": {
      "col": 30,
      "row": 29
    },
    "197": {
      "col": 17,
      "row": 31
    },
    "198": {
      "col": 4,
      "row": 39
    },
    "199": {
      "col": 20,
      "row": 48
    },
    "200": {
      "col": 21,
      "row": 48
    },
    "201": {
      "col": 22,
      "row": 48
    },
    "202": {
      "col": 23,
      "row": 48
    },
    "203": {
      "col": 24,
      "row": 48
    },
    "204": {
      "col": 3,
      "row": 38
    },
    "205": {
      "col": 2,
      "row": 56
    },
    "206": {
      "col": 3,
      "row": 56
    },
    "207": {
      "col": 4,
      "row": 56
    },
    "208": {
      "col": 13,
      "row": 45
    },
    "209": {
      "col": 10,
      "row": 32
    },
    "210": {
      "col": 18,
      "row": 34
    },
    "211": {
      "col": 31,
      "row": 29
    },
    "212": {
      "col": 18,
      "row": 40
    },
    "213": {
      "col": 3,
      "row": 45
    },
    "214": {
      "col": 25,
      "row": 48
    },
    "215": {
      "col": 20,
      "row": 41
    },
    "216": {
      "col": 31,
      "row": 42
    },
    "217": {
      "col": 5,
      "row": 56
    },
    "218": {
      "col": 28,
      "row": 55
    },
    "219": {
      "col": 6,
      "row": 56
    },
    "220": {
      "col": 7,
      "row": 56
    },
    "221": {
      "col": 8,
      "row": 56
    },
    "222": {
      "col": 26,
      "row": 48
    },
    "223": {
      "col": 27,
      "row": 48
    },
    "224": {
      "col": 10,
      "row": 45
    },
    "225": {
      "col": 30,
      "row": 42
    },
    "226": {
      "col": 25,
      "row": 39
    },
    "227": {
      "col": 31,
      "row": 30
    },
    "228": {
      "col": 11,
      "row": 44
    },
    "229": {
      "col": 14,
      "row": 45
    },
    "230": {
      "col": 5,
      "row": 39
    },
    "231": {
      "col": 28,
      "row": 31
    },
    "232": {
      "col": 25,
      "row": 37
    },
    "233": {
      "col": 19,
      "row": 40
    },
    "234": {
      "col": 0,
      "row": 35
    },
    "235": {
      "col": 28,
      "row": 48
    },
    "236": {
      "col": 27,
      "row": 32
    },
    "237": {
      "col": 11,
      "row": 45
    },
    "238": {
      "col": 11,
      "row": 33
    },
    "239": {
      "col": 3,
      "row": 29
    },
    "240": {
      "col": 0,
      "row": 43
    },
    "241": {
      "col": 1,
      "row": 43
    },
    "242": {
      "col": 9,
      "row": 56
    },
    "243": {
      "col": 10,
      "row": 56
    },
    "244": {
      "col": 21,
      "row": 41
    },
    "245": {
      "col": 20,
      "row": 40
    },
    "246": {
      "col": 29,
      "row": 48
    },
    "247": {
      "col": 1,
      "row": 0
    },
    "248": {
      "col": 11,
      "row": 56
    },
    "249": {
      "col": 12,
      "row": 56
    },
    "250": {
      "col": 19,
      "row": 31
    },
    "251": {
      "col": 13,
      "row": 56
    },
    "252": {
      "col": 9,
      "row": 40
    },
    "253": {
      "col": 30,
      "row": 48
    },
    "254": {
      "col": 31,
      "row": 48
    },
    "255": {
      "col": 17,
      "row": 33
    },
    "256": {
      "col": 9,
      "row": 39
    },
    "257": {
      "col": 0,
      "row": 30
    },
    "258": {
      "col": 0,
      "row": 49
    },
    "259": {
      "col": 18,
      "row": 31
    },
    "260": {
      "col": 22,
      "row": 41
    },
    "261": {
      "col": 10,
      "row": 39
    },
    "262": {
      "col": 12,
      "row": 33
    },
    "263": {
      "col": 14,
      "row": 56
    },
    "264": {
      "col": 23,
      "row": 41
    },
    "265": {
      "col": 15,
      "row": 56
    },
    "266": {
      "col": 16,
      "row": 56
    },
    "267": {
      "col": 11,
      "row": 29
    },
    "268": {
      "col": 17,
      "row": 56
    },
    "269": {
      "col": 11,
      "row": 41
    },
    "270": {
      "col": 8,
      "row": 44
    },
    "271": {
      "col": 19,
      "row": 36
    },
    "272": {
      "col": 20,
      "row": 36
    },
    "273": {
      "col": 1,
      "row": 49
    },
    "274": {
      "col": 2,
      "row": 49
    },
    "275": {
      "col": 1,
      "row": 35
    },
    "276": {
      "col": 26,
      "row": 37
    },
    "277": {
      "col": 2,
      "row": 35
    },
    "278": {
      "col": 18,
      "row": 33
    },
    "279": {
      "col": 11,
      "row": 32
    },
    "280": {
      "col": 20,
      "row": 32
    },
    "281": {
      "col": 24,
      "row": 39
    },
    "282": {
      "col": 21,
      "row": 36
    },
    "283": {
      "col": 25,
      "row": 35
    },
    "284": {
      "col": 18,
      "row": 56
    },
    "285": {
      "col": 24,
      "row": 41
    },
    "286": {
      "col": 21,
      "row": 40
    },
    "287": {
      "col": 20,
      "row": 31
    },
    "288": {
      "col": 19,
      "row": 33
    },
    "289": {
      "col": 22,
      "row": 31
    },
    "290": {
      "col": 19,
      "row": 56
    },
    "291": {
      "col": 2,
      "row": 43
    },
    "292": {
      "col": 20,
      "row": 56
    },
    "293": {
      "col": 21,
      "row": 56
    },
    "294": {
      "col": 21,
      "row": 32
    },
    "295": {
      "col": 22,
      "row": 56
    },
    "296": {
      "col": 22,
      "row": 32
    },
    "297": {
      "col": 9,
      "row": 35
    },
    "298": {
      "col": 23,
      "row": 56
    },
    "299": {
      "col": 24,
      "row": 56
    },
    "300": {
      "col": 25,
      "row": 56
    },
    "301": {
      "col": 19,
      "row": 34
    },
    "302": {
      "col": 26,
      "row": 56
    },
    "303": {
      "col": 0,
      "row": 31
    },
    "304": {
      "col": 3,
      "row": 35
    },
    "305": {
      "col": 1,
      "row": 31
    },
    "306": {
      "col": 2,
      "row": 31
    },
    "307": {
      "col": 22,
      "row": 36
    },
    "308": {
      "col": 23,
      "row": 36
    },
    "309": {
      "col": 24,
      "row": 36
    },
    "310": {
      "col": 14,
      "row": 29
    },
    "311": {
      "col": 27,
      "row": 56
    },
    "312": {
      "col": 1,
      "row": 30
    },
    "313": {
      "col": 25,
      "row": 41
    },
    "314": {
      "col": 26,
      "row": 41
    },
    "315": {
      "col": 27,
      "row": 41
    },
    "316": {
      "col": 12,
      "row": 29
    },
    "317": {
      "col": 28,
      "row": 56
    },
    "318": {
      "col": 29,
      "row": 56
    },
    "319": {
      "col": 30,
      "row": 56
    },
    "320": {
      "col": 24,
      "row": 31
    },
    "321": {
      "col": 20,
      "row": 33
    },
    "322": {
      "col": 22,
      "row": 31
    },
    "323": {
      "col": 11,
      "row": 39
    },
    "324": {
      "col": 5,
      "row": 41
    },
    "325": {
      "col": 23,
      "row": 31
    },
    "326": {
      "col": 31,
      "row": 56
    },
    "327": {
      "col": 0,
      "row": 57
    },
    "328": {
      "col": 1,
      "row": 57
    },
    "329": {
      "col": 2,
      "row": 57
    },
    "330": {
      "col": 28,
      "row": 41
    },
    "331": {
      "col": 4,
      "row": 35
    },
    "332": {
      "col": 3,
      "row": 57
    },
    "333": {
      "col": 4,
      "row": 57
    },
    "334": {
      "col": 3,
      "row": 49
    },
    "335": {
      "col": 5,
      "row": 57
    },
    "336": {
      "col": 4,
      "row": 49
    },
    "337": {
      "col": 25,
      "row": 36
    },
    "338": {
      "col": 26,
      "row": 36
    },
    "339": {
      "col": 6,
      "row": 39
    },
    "340": {
      "col": 27,
      "row": 36
    },
    "341": {
      "col": 12,
      "row": 32
    },
    "342": {
      "col": 26,
      "row": 33
    },
    "343": {
      "col": 18,
      "row": 36
    },
    "344": {
      "col": 5,
      "row": 49
    },
    "345": {
      "col": 6,
      "row": 57
    },
    "346": {
      "col": 7,
      "row": 57
    },
    "347": {
      "col": 2,
      "row": 30
    },
    "348": {
      "col": 28,
      "row": 39
    },
    "349": {
      "col": 22,
      "row": 33
    },
    "350": {
      "col": 29,
      "row": 41
    },
    "351": {
      "col": 17,
      "row": 37
    },
    "352": {
      "col": 13,
      "row": 29
    },
    "353": {
      "col": 8,
      "row": 57
    },
    "354": {
      "col": 20,
      "row": 44
    },
    "355": {
      "col": 21,
      "row": 44
    },
    "356": {
      "col": 30,
      "row": 41
    },
    "357": {
      "col": 9,
      "row": 57
    },
    "358": {
      "col": 22,
      "row": 44
    },
    "359": {
      "col": 23,
      "row": 44
    },
    "360": {
      "col": 10,
      "row": 57
    },
    "361": {
      "col": 11,
      "row": 57
    },
    "362": {
      "col": 8,
      "row": 33
    },
    "363": {
      "col": 12,
      "row": 57
    },
    "364": {
      "col": 13,
      "row": 57
    },
    "365": {
      "col": 14,
      "row": 57
    },
    "366": {
      "col": 29,
      "row": 32
    },
    "367": {
      "col": 12,
      "row": 39
    },
    "368": {
      "col": 6,
      "row": 49
    },
    "369": {
      "col": 5,
      "row": 35
    },
    "370": {
      "col": 15,
      "row": 57
    },
    "371": {
      "col": 22,
      "row": 40
    },
    "372": {
      "col": 3,
      "row": 43
    },
    "373": {
      "col": 31,
      "row": 41
    },
    "374": {
      "col": 16,
      "row": 57
    },
    "375": {
      "col": 7,
      "row": 49
    },
    "376": {
      "col": 4,
      "row": 43
    },
    "377": {
      "col": 18,
      "row": 37
    },
    "378": {
      "col": 28,
      "row": 32
    },
    "379": {
      "col": 17,
      "row": 57
    },
    "380": {
      "col": 6,
      "row": 43
    },
    "381": {
      "col": 8,
      "row": 49
    },
    "382": {
      "col": 9,
      "row": 49
    },
    "383": {
      "col": 10,
      "row": 49
    },
    "384": {
      "col": 18,
      "row": 57
    },
    "385": {
      "col": 11,
      "row": 49
    },
    "386": {
      "col": 19,
      "row": 57
    },
    "387": {
      "col": 21,
      "row": 34
    },
    "388": {
      "col": 20,
      "row": 57
    },
    "389": {
      "col": 12,
      "row": 49
    },
    "390": {
      "col": 9,
      "row": 33
    },
    "391": {
      "col": 19,
      "row": 37
    },
    "392": {
      "col": 5,
      "row": 43
    },
    "394": {
      "col": 29,
      "row": 31
    },
    "395": {
      "col": 27,
      "row": 37
    },
    "396": {
      "col": 21,
      "row": 57
    },
    "397": {
      "col": 14,
      "row": 49
    },
    "398": {
      "col": 13,
      "row": 39
    },
    "399": {
      "col": 22,
      "row": 57
    },
    "400": {
      "col": 31,
      "row": 39
    },
    "401": {
      "col": 10,
      "row": 35
    },
    "402": {
      "col": 23,
      "row": 57
    },
    "403": {
      "col": 11,
      "row": 35
    },
    "404": {
      "col": 4,
      "row": 45
    },
    "405": {
      "col": 31,
      "row": 32
    },
    "406": {
      "col": 24,
      "row": 57
    },
    "407": {
      "col": 25,
      "row": 57
    },
    "408": {
      "col": 12,
      "row": 37
    },
    "409": {
      "col": 15,
      "row": 49
    },
    "410": {
      "col": 26,
      "row": 57
    },
    "411": {
      "col": 19,
      "row": 44
    },
    "412": {
      "col": 7,
      "row": 39
    },
    "413": {
      "col": 7,
      "row": 43
    },
    "414": {
      "col": 27,
      "row": 57
    },
    "415": {
      "col": 13,
      "row": 33
    },
    "416": {
      "col": 31,
      "row": 35
    },
    "417": {
      "col": 15,
      "row": 29
    },
    "418": {
      "col": 15,
      "row": 52
    },
    "419": {
      "col": 16,
      "row": 49
    },
    "420": {
      "col": 17,
      "row": 49
    },
    "421": {
      "col": 0,
      "row": 33
    },
    "422": {
      "col": 28,
      "row": 57
    },
    "423": {
      "col": 4,
      "row": 29
    },
    "424": {
      "col": 12,
      "row": 35
    },
    "426": {
      "col": 29,
      "row": 57
    },
    "427": {
      "col": 18,
      "row": 49
    },
    "428": {
      "col": 28,
      "row": 36
    },
    "429": {
      "col": 29,
      "row": 36
    },
    "430": {
      "col": 14,
      "row": 33
    },
    "431": {
      "col": 16,
      "row": 33
    },
    "432": {
      "col": 26,
      "row": 35
    },
    "433": {
      "col": 13,
      "row": 32
    },
    "434": {
      "col": 19,
      "row": 49
    },
    "435": {
      "col": 14,
      "row": 39
    },
    "436": {
      "col": 12,
      "row": 41
    },
    "437": {
      "col": 30,
      "row": 57
    },
    "438": {
      "col": 31,
      "row": 57
    },
    "439": {
      "col": 20,
      "row": 49
    },
    "440": {
      "col": 22,
      "row": 34
    },
    "441": {
      "col": 21,
      "row": 49
    },
    "442": {
      "col": 8,
      "row": 43
    },
    "443": {
      "col": 0,
      "row": 58
    },
    "444": {
      "col": 1,
      "row": 58
    },
    "445": {
      "col": 2,
      "row": 58
    },
    "446": {
      "col": 5,
      "row": 45
    },
    "447": {
      "col": 1,
      "row": 44
    },
    "448": {
      "col": 22,
      "row": 49
    },
    "449": {
      "col": 10,
      "row": 43
    },
    "450": {
      "col": 11,
      "row": 43
    },
    "451": {
      "col": 23,
      "row": 49
    },
    "452": {
      "col": 3,
      "row": 58
    },
    "453": {
      "col": 23,
      "row": 34
    },
    "454": {
      "col": 13,
      "row": 35
    },
    "455": {
      "col": 25,
      "row": 49
    },
    "456": {
      "col": 16,
      "row": 29
    },
    "457": {
      "col": 30,
      "row": 45
    },
    "458": {
      "col": 26,
      "row": 49
    },
    "459": {
      "col": 4,
      "row": 38
    },
    "460": {
      "col": 5,
      "row": 38
    },
    "461": {
      "col": 6,
      "row": 38
    },
    "462": {
      "col": 7,
      "row": 38
    },
    "463": {
      "col": 4,
      "row": 58
    },
    "464": {
      "col": 15,
      "row": 39
    },
    "465": {
      "col": 12,
      "row": 44
    },
    "466": {
      "col": 5,
      "row": 58
    },
    "467": {
      "col": 6,
      "row": 58
    },
    "468": {
      "col": 7,
      "row": 58
    },
    "469": {
      "col": 11,
      "row": 37
    },
    "470": {
      "col": 0,
      "row": 36
    },
    "471": {
      "col": 8,
      "row": 38
    },
    "472": {
      "col": 14,
      "row": 32
    },
    "473": {
      "col": 1,
      "row": 46
    },
    "474": {
      "col": 1,
      "row": 33
    },
    "475": {
      "col": 8,
      "row": 58
    },
    "476": {
      "col": 9,
      "row": 58
    },
    "477": {
      "col": 30,
      "row": 31
    },
    "478": {
      "col": 2,
      "row": 33
    },
    "479": {
      "col": 15,
      "row": 33
    },
    "480": {
      "col": 27,
      "row": 33
    },
    "481": {
      "col": 6,
      "row": 35
    },
    "482": {
      "col": 10,
      "row": 58
    },
    "483": {
      "col": 11,
      "row": 58
    },
    "484": {
      "col": 12,
      "row": 58
    },
    "485": {
      "col": 12,
      "row": 43
    },
    "486": {
      "col": 6,
      "row": 41
    },
    "487": {
      "col": 21,
      "row": 33
    },
    "488": {
      "col": 27,
      "row": 49
    },
    "489": {
      "col": 13,
      "row": 58
    },
    "490": {
      "col": 14,
      "row": 58
    },
    "491": {
      "col": 15,
      "row": 35
    },
    "492": {
      "col": 15,
      "row": 58
    },
    "493": {
      "col": 16,
      "row": 35
    },
    "494": {
      "col": 17,
      "row": 35
    },
    "495": {
      "col": 18,
      "row": 35
    },
    "496": {
      "col": 14,
      "row": 35
    },
    "497": {
      "col": 28,
      "row": 49
    },
    "498": {
      "col": 29,
      "row": 49
    },
    "499": {
      "col": 1,
      "row": 36
    },
    "500": {
      "col": 13,
      "row": 44
    },
    "501": {
      "col": 9,
      "row": 38
    },
    "502": {
      "col": 10,
      "row": 38
    },
    "503": {
      "col": 11,
      "row": 38
    },
    "504": {
      "col": 12,
      "row": 38
    },
    "505": {
      "col": 30,
      "row": 49
    },
    "506": {
      "col": 31,
      "row": 49
    },
    "507": {
      "col": 29,
      "row": 49
    },
    "508": {
      "col": 0,
      "row": 32
    },
    "509": {
      "col": 19,
      "row": 35
    },
    "510": {
      "col": 3,
      "row": 31
    },
    "511": {
      "col": 17,
      "row": 29
    },
    "512": {
      "col": 4,
      "row": 31
    },
    "513": {
      "col": 1,
      "row": 50
    },
    "514": {
      "col": 5,
      "row": 31
    },
    "515": {
      "col": 28,
      "row": 37
    },
    "516": {
      "col": 14,
      "row": 43
    },
    "517": {
      "col": 2,
      "row": 50
    },
    "518": {
      "col": 3,
      "row": 33
    },
    "519": {
      "col": 16,
      "row": 58
    },
    "520": {
      "col": 27,
      "row": 35
    },
    "521": {
      "col": 3,
      "row": 50
    },
    "522": {
      "col": 17,
      "row": 58
    },
    "523": {
      "col": 18,
      "row": 58
    },
    "524": {
      "col": 7,
      "row": 35
    },
    "525": {
      "col": 6,
      "row": 31
    },
    "526": {
      "col": 7,
      "row": 31
    },
    "527": {
      "col": 4,
      "row": 50
    },
    "528": {
      "col": 19,
      "row": 58
    },
    "529": {
      "col": 5,
      "row": 50
    },
    "530": {
      "col": 16,
      "row": 39
    },
    "531": {
      "col": 20,
      "row": 58
    },
    "532": {
      "col": 16,
      "row": 43
    },
    "533": {
      "col": 21,
      "row": 58
    },
    "534": {
      "col": 1,
      "row": 32
    },
    "535": {
      "col": 22,
      "row": 58
    },
    "536": {
      "col": 23,
      "row": 58
    },
    "537": {
      "col": 9,
      "row": 31
    },
    "538": {
      "col": 20,
      "row": 35
    },
    "539": {
      "col": 6,
      "row": 50
    },
    "540": {
      "col": 30,
      "row": 36
    },
    "541": {
      "col": 23,
      "row": 40
    },
    "542": {
      "col": 31,
      "row": 36
    },
    "543": {
      "col": 0,
      "row": 37
    },
    "544": {
      "col": 24,
      "row": 58
    },
    "545": {
      "col": 8,
      "row": 31
    },
    "546": {
      "col": 13,
      "row": 38
    },
    "547": {
      "col": 2,
      "row": 44
    },
    "548": {
      "col": 13,
      "row": 37
    },
    "549": {
      "col": 14,
      "row": 38
    },
    "550": {
      "col": 15,
      "row": 36
    },
    "551": {
      "col": 21,
      "row": 35
    },
    "552": {
      "col": 25,
      "row": 58
    },
    "553": {
      "col": 7,
      "row": 50
    },
    "554": {
      "col": 2,
      "row": 36
    },
    "555": {
      "col": 26,
      "row": 58
    },
    "556": {
      "col": 15,
      "row": 38
    },
    "557": {
      "col": 8,
      "row": 50
    },
    "558": {
      "col": 9,
      "row": 50
    },
    "559": {
      "col": 16,
      "row": 38
    },
    "560": {
      "col": 17,
      "row": 38
    },
    "561": {
      "col": 18,
      "row": 38
    },
    "562": {
      "col": 19,
      "row": 38
    },
    "563": {
      "col": 20,
      "row": 38
    },
    "564": {
      "col": 10,
      "row": 50
    },
    "565": {
      "col": 31,
      "row": 45
    },
    "566": {
      "col": 24,
      "row": 32
    },
    "567": {
      "col": 27,
      "row": 58
    },
    "568": {
      "col": 28,
      "row": 58
    },
    "569": {
      "col": 11,
      "row": 50
    },
    "570": {
      "col": 10,
      "row": 31
    },
    "571": {
      "col": 12,
      "row": 50
    },
    "572": {
      "col": 29,
      "row": 58
    },
    "573": {
      "col": 13,
      "row": 50
    },
    "574": {
      "col": 14,
      "row": 50
    },
    "575": {
      "col": 10,
      "row": 33
    },
    "576": {
      "col": 30,
      "row": 58
    },
    "578": {
      "col": 31,
      "row": 58
    },
    "579": {
      "col": 15,
      "row": 50
    },
    "580": {
      "col": 0,
      "row": 59
    },
    "581": {
      "col": 14,
      "row": 37
    },
    "582": {
      "col": 11,
      "row": 31
    },
    "583": {
      "col": 1,
      "row": 59
    },
    "584": {
      "col": 12,
      "row": 31
    },
    "585": {
      "col": 24,
      "row": 40
    },
    "586": {
      "col": 16,
      "row": 52
    },
    "587": {
      "col": 0,
      "row": 46
    },
    "588": {
      "col": 24,
      "row": 44
    },
    "589": {
      "col": 21,
      "row": 38
    },
    "590": {
      "col": 22,
      "row": 38
    },
    "591": {
      "col": 23,
      "row": 38
    },
    "592": {
      "col": 24,
      "row": 38
    },
    "593": {
      "col": 25,
      "row": 38
    },
    "594": {
      "col": 24,
      "row": 52
    },
    "595": {
      "col": 24,
      "row": 49
    },
    "596": {
      "col": 26,
      "row": 52
    },
    "597": {
      "col": 20,
      "row": 43
    },
    "598": {
      "col": 16,
      "row": 50
    },
    "599": {
      "col": 25,
      "row": 44
    },
    "600": {
      "col": 26,
      "row": 44
    },
    "601": {
      "col": 8,
      "row": 30
    },
    "602": {
      "col": 9,
      "row": 30
    },
    "603": {
      "col": 31,
      "row": 38
    },
    "604": {
      "col": 3,
      "row": 36
    },
    "605": {
      "col": 18,
      "row": 29
    },
    "606": {
      "col": 13,
      "row": 31
    },
    "607": {
      "col": 4,
      "row": 36
    },
    "608": {
      "col": 17,
      "row": 50
    },
    "609": {
      "col": 18,
      "row": 50
    },
    "611": {
      "col": 25,
      "row": 52
    },
    "612": {
      "col": 5,
      "row": 36
    },
    "614": {
      "col": 24,
      "row": 34
    },
    "615": {
      "col": 14,
      "row": 31
    },
    "616": {
      "col": 26,
      "row": 38
    },
    "617": {
      "col": 10,
      "row": 30
    },
    "618": {
      "col": 11,
      "row": 30
    },
    "619": {
      "col": 19,
      "row": 50
    },
    "620": {
      "col": 22,
      "row": 35
    },
    "621": {
      "col": 23,
      "row": 35
    },
    "622": {
      "col": 3,
      "row": 44
    },
    "623": {
      "col": 28,
      "row": 35
    },
    "624": {
      "col": 12,
      "row": 30
    },
    "630": {
      "col": 24,
      "row": 35
    },
    "631": {
      "col": 20,
      "row": 50
    },
    "632": {
      "col": 6,
      "row": 45
    },
    "633": {
      "col": 28,
      "row": 33
    },
    "634": {
      "col": 23,
      "row": 33
    },
    "635": {
      "col": 25,
      "row": 34
    },
    "636": {
      "col": 22,
      "row": 43
    },
    "637": {
      "col": 23,
      "row": 43
    },
    "638": {
      "col": 24,
      "row": 43
    },
    "639": {
      "col": 16,
      "row": 36
    },
    "640": {
      "col": 23,
      "row": 29
    },
    "641": {
      "col": 15,
      "row": 32
    },
    "642": {
      "col": 13,
      "row": 41
    },
    "643": {
      "col": 13,
      "row": 30
    },
    "644": {
      "col": 14,
      "row": 30
    },
    "645": {
      "col": 15,
      "row": 30
    },
    "646": {
      "col": 16,
      "row": 30
    },
    "648": {
      "col": 21,
      "row": 50
    },
    "649": {
      "col": 25,
      "row": 32
    },
    "651": {
      "col": 22,
      "row": 50
    },
    "657": {
      "col": 1,
      "row": 40
    },
    "658": {
      "col": 4,
      "row": 33
    },
    "659": {
      "col": 23,
      "row": 50
    },
    "660": {
      "col": 25,
      "row": 50
    },
    "661": {
      "col": 19,
      "row": 29
    },
    "662": {
      "col": 26,
      "row": 50
    },
    "663": {
      "col": 27,
      "row": 50
    },
    "664": {
      "col": 0,
      "row": 39
    },
    "665": {
      "col": 1,
      "row": 32
    },
    "666": {
      "col": 28,
      "row": 50
    },
    "667": {
      "col": 1,
      "row": 32
    },
    "673": {
      "col": 2,
      "row": 44
    },
    "675": {
      "col": 17,
      "row": 30
    },
    "676": {
      "col": 18,
      "row": 30
    },
    "677": {
      "col": 29,
      "row": 50
    },
    "679": {
      "col": 15,
      "row": 31
    },
    "685": {
      "col": 24,
      "row": 50
    },
    "687": {
      "col": 17,
      "row": 31
    },
    "688": {
      "col": 26,
      "row": 34
    },
    "689": {
      "col": 26,
      "row": 43
    },
    "690": {
      "col": 5,
      "row": 32
    },
    "691": {
      "col": 18,
      "row": 39
    },
    "692": {
      "col": 27,
      "row": 45
    },
    "693": {
      "col": 30,
      "row": 50
    },
    "696": {
      "col": 31,
      "row": 50
    },
    "697": {
      "col": 19,
      "row": 30
    },
    "698": {
      "col": 0,
      "row": 51
    },
    "699": {
      "col": 1,
      "row": 51
    },
    "701": {
      "col": 21,
      "row": 30
    },
    "702": {
      "col": 24,
      "row": 33
    },
    "703": {
      "col": 20,
      "row": 30
    },
    "705": {
      "col": 2,
      "row": 51
    },
    "711": {
      "col": 7,
      "row": 41
    },
    "712": {
      "col": 3,
      "row": 51
    },
    "715": {
      "col": 26,
      "row": 45
    },
    "718": {
      "col": 4,
      "row": 51
    },
    "720": {
      "col": 21,
      "row": 45
    },
    "721": {
      "col": 5,
      "row": 51
    },
    "722": {
      "col": 29,
      "row": 45
    },
    "723": {
      "col": 6,
      "row": 51
    },
    "724": {
      "col": 1,
      "row": 37
    },
    "725": {
      "col": 2,
      "row": 37
    },
    "726": {
      "col": 3,
      "row": 37
    },
    "727": {
      "col": 29,
      "row": 33
    },
    "728": {
      "col": 23,
      "row": 30
    },
    "730": {
      "col": 16,
      "row": 32
    },
    "732": {
      "col": 7,
      "row": 51
    },
    "733": {
      "col": 8,
      "row": 51
    },
    "737": {
      "col": 9,
      "row": 51
    },
    "738": {
      "col": 11,
      "row": 36
    },
    "739": {
      "col": 10,
      "row": 51
    },
    "741": {
      "col": 24,
      "row": 30
    },
    "743": {
      "col": 24,
      "row": 29
    },
    "744": {
      "col": 12,
      "row": 36
    },
    "748": {
      "col": 14,
      "row": 44
    },
    "749": {
      "col": 15,
      "row": 44
    },
    "750": {
      "col": 16,
      "row": 44
    },
    "751": {
      "col": 27,
      "row": 44
    },
    "752": {
      "col": 28,
      "row": 44
    },
    "754": {
      "col": 27,
      "row": 34
    },
    "755": {
      "col": 29,
      "row": 35
    },
    "756": {
      "col": 25,
      "row": 30
    },
    "757": {
      "col": 11,
      "row": 51
    },
    "759": {
      "col": 30,
      "row": 33
    },
    "760": {
      "col": 12,
      "row": 51
    },
    "762": {
      "col": 2,
      "row": 40
    },
    "763": {
      "col": 13,
      "row": 51
    },
    "764": {
      "col": 20,
      "row": 29
    },
    "765": {
      "col": 21,
      "row": 29
    },
    "766": {
      "col": 26,
      "row": 30
    },
    "768": {
      "col": 13,
      "row": 36
    },
    "769": {
      "col": 22,
      "row": 29
    },
    "771": {
      "col": 30,
      "row": 43
    },
    "773": {
      "col": 14,
      "row": 51
    },
    "774": {
      "col": 6,
      "row": 32
    },
    "777": {
      "col": 15,
      "row": 51
    },
    "778": {
      "col": 16,
      "row": 51
    },
    "779": {
      "col": 5,
      "row": 37
    },
    "783": {
      "col": 27,
      "row": 30
    },
    "784": {
      "col": 28,
      "row": 30
    },
    "785": {
      "col": 29,
      "row": 30
    },
    "786": {
      "col": 17,
      "row": 51
    },
    "789": {
      "col": 18,
      "row": 51
    },
    "790": {
      "col": 19,
      "row": 51
    },
    "791": {
      "col": 20,
      "row": 51
    },
    "792": {
      "col": 7,
      "row": 32
    },
    "793": {
      "col": 21,
      "row": 51
    },
    "794": {
      "col": 22,
      "row": 51
    },
    "795": {
      "col": 30,
      "row": 30
    },
    "796": {
      "col": 23,
      "row": 51
    },
    "798": {
      "col": 5,
      "row": 33
    },
    "799": {
      "col": 24,
      "row": 51
    },
    "800": {
      "col": 31,
      "row": 33
    },
    "801": {
      "col": 0,
      "row": 34
    },
    "802": {
      "col": 1,
      "row": 34
    },
    "804": {
      "col": 6,
      "row": 33
    },
    "805": {
      "col": 1,
      "row": 39
    },
    "807": {
      "col": 25,
      "row": 51
    },
    "808": {
      "col": 8,
      "row": 35
    },
    "809": {
      "col": 26,
      "row": 51
    },
    "811": {
      "col": 6,
      "row": 37
    },
    "813": {
      "col": 27,
      "row": 51
    },
    "815": {
      "col": 28,
      "row": 51
    },
    "816": {
      "col": 29,
      "row": 51
    },
    "818": {
      "col": 31,
      "row": 43
    },
    "819": {
      "col": 30,
      "row": 51
    },
    "820": {
      "col": 31,
      "row": 51
    },
    "821": {
      "col": 2,
      "row": 34
    },
    "822": {
      "col": 3,
      "row": 34
    },
    "824": {
      "col": 0,
      "row": 52
    },
    "825": {
      "col": 14,
      "row": 36
    },
    "828": {
      "col": 1,
      "row": 52
    },
    "829": {
      "col": 3,
      "row": 30
    },
    "830": {
      "col": 17,
      "row": 44
    },
    "831": {
      "col": 2,
      "row": 52
    },
    "832": {
      "col": 3,
      "row": 52
    },
    "836": {
      "col": 4,
      "row": 52
    },
    "838": {
      "col": 28,
      "row": 34
    },
    "839": {
      "col": 23,
      "row": 45
    },
    "840": {
      "col": 5,
      "row": 30
    },
    "844": {
      "col": 5,
      "row": 52
    },
    "845": {
      "col": 6,
      "row": 52
    },
    "847": {
      "col": 7,
      "row": 52
    },
    "848": {
      "col": 8,
      "row": 52
    },
    "850": {
      "col": 6,
      "row": 30
    },
    "851": {
      "col": 9,
      "row": 52
    },
    "852": {
      "col": 10,
      "row": 52
    },
    "853": {
      "col": 7,
      "row": 30
    },
    "856": {
      "col": 24,
      "row": 45
    },
    "857": {
      "col": 11,
      "row": 52
    },
    "858": {
      "col": 0,
      "row": 44
    },
    "860": {
      "col": 12,
      "row": 52
    },
    "861": {
      "col": 25,
      "row": 33
    },
    "862": {
      "col": 13,
      "row": 52
    }
  },
  "items": {
    "0": {
      "col": -96,
      "row": -127
    },
    "1": {
      "col": 20,
      "row": 5
    },
    "2": {
      "col": 20,
      "row": 5
    },
    "3": {
      "col": 20,
      "row": 5
    },
    "4": {
      "col": 20,
      "row": 5
    },
    "5": {
      "col": 20,
      "row": 5
    },
    "6": {
      "col": 20,
      "row": 5
    },
    "7": {
      "col": 20,
      "row": 5
    },
    "8": {
      "col": 20,
      "row": 5
    },
    "9": {
      "col": 20,
      "row": 5
    },
    "10": {
      "col": 20,
      "row": 5
    },
    "11": {
      "col": 20,
      "row": 5
    },
    "12": {
      "col": 20,
      "row": 5
    },
    "13": {
      "col": 20,
      "row": 5
    },
    "14": {
      "col": 20,
      "row": 5
    },
    "15": {
      "col": 20,
      "row": 5
    },
    "16": {
      "col": 20,
      "row": 5
    },
    "17": {
      "col": 20,
      "row": 5
    },
    "18": {
      "col": 20,
      "row": 5
    },
    "19": {
      "col": 20,
      "row": 5
    },
    "20": {
      "col": 20,
      "row": 5
    },
    "21": {
      "col": 4,
      "row": 14
    },
    "22": {
      "col": 2,
      "row": 14
    },
    "23": {
      "col": 3,
      "row": 14
    },
    "24": {
      "col": 5,
      "row": 14
    },
    "25": {
      "col": 6,
      "row": 14
    },
    "26": {
      "col": 0,
      "row": 14
    },
    "27": {
      "col": 0,
      "row": 14
    },
    "29": {
      "col": 9,
      "row": 53
    },
    "30": {
      "col": 13,
      "row": 10
    },
    "31": {
      "col": 14,
      "row": 10
    },
    "32": {
      "col": 23,
      "row": 10
    },
    "33": {
      "col": 21,
      "row": 10
    },
    "34": {
      "col": 24,
      "row": 10
    },
    "35": {
      "col": 20,
      "row": 10
    },
    "36": {
      "col": 30,
      "row": 10
    },
    "37": {
      "col": 28,
      "row": 10
    },
    "38": {
      "col": 16,
      "row": 10
    },
    "39": {
      "col": 22,
      "row": 10
    },
    "40": {
      "col": 29,
      "row": 10
    },
    "41": {
      "col": 27,
      "row": 10
    },
    "42": {
      "col": 25,
      "row": 10
    },
    "43": {
      "col": 15,
      "row": 10
    },
    "44": {
      "col": 17,
      "row": 10
    },
    "45": {
      "col": 19,
      "row": 10
    },
    "46": {
      "col": 18,
      "row": 10
    },
    "47": {
      "col": 14,
      "row": 10
    },
    "48": {
      "col": 6,
      "row": 11
    },
    "49": {
      "col": 31,
      "row": 10
    },
    "50": {
      "col": 3,
      "row": 11
    },
    "51": {
      "col": 7,
      "row": 11
    },
    "52": {
      "col": 4,
      "row": 11
    },
    "53": {
      "col": 1,
      "row": 11
    },
    "54": {
      "col": 2,
      "row": 11
    },
    "55": {
      "col": 0,
      "row": 11
    },
    "56": {
      "col": 5,
      "row": 11
    },
    "57": {
      "col": 8,
      "row": 11
    },
    "58": {
      "col": 13,
      "row": 11
    },
    "59": {
      "col": 16,
      "row": 11
    },
    "60": {
      "col": 18,
      "row": 11
    },
    "61": {
      "col": 19,
      "row": 11
    },
    "62": {
      "col": 11,
      "row": 11
    },
    "63": {
      "col": 15,
      "row": 11
    },
    "64": {
      "col": 9,
      "row": 11
    },
    "65": {
      "col": 10,
      "row": 11
    },
    "66": {
      "col": 12,
      "row": 11
    },
    "67": {
      "col": 21,
      "row": 11
    },
    "68": {
      "col": 14,
      "row": 11
    },
    "69": {
      "col": 20,
      "row": 11
    },
    "70": {
      "col": 17,
      "row": 11
    },
    "71": {
      "col": 22,
      "row": 11
    },
    "72": {
      "col": 23,
      "row": 11
    },
    "73": {
      "col": 24,
      "row": 11
    },
    "74": {
      "col": 25,
      "row": 11
    },
    "75": {
      "col": 26,
      "row": 11
    },
    "76": {
      "col": 27,
      "row": 11
    },
    "77": {
      "col": 28,
      "row": 11
    },
    "78": {
      "col": 0,
      "row": 12
    },
    "79": {
      "col": 1,
      "row": 12
    },
    "80": {
      "col": 2,
      "row": 12
    },
    "81": {
      "col": 3,
      "row": 12
    },
    "82": {
      "col": 4,
      "row": 12
    },
    "83": {
      "col": 5,
      "row": 12
    },
    "84": {
      "col": 15,
      "row": 14
    },
    "85": {
      "col": 16,
      "row": 14
    },
    "86": {
      "col": 17,
      "row": 14
    },
    "87": {
      "col": 12,
      "row": 14
    },
    "88": {
      "col": 13,
      "row": 14
    },
    "89": {
      "col": 17,
      "row": 14
    },
    "90": {
      "col": 9,
      "row": 9
    },
    "91": {
      "col": 14,
      "row": 8
    },
    "92": {
      "col": 15,
      "row": 8
    },
    "93": {
      "col": 16,
      "row": 8
    },
    "94": {
      "col": 24,
      "row": 7
    },
    "95": {
      "col": 25,
      "row": 7
    },
    "96": {
      "col": 26,
      "row": 7
    },
    "97": {
      "col": 27,
      "row": 7
    },
    "98": {
      "col": 28,
      "row": 7
    },
    "99": {
      "col": 29,
      "row": 7
    },
    "100": {
      "col": 30,
      "row": 7
    },
    "101": {
      "col": 12,
      "row": 9
    },
    "102": {
      "col": 11,
      "row": 9
    },
    "103": {
      "col": 13,
      "row": 9
    },
    "104": {
      "col": 14,
      "row": 9
    },
    "105": {
      "col": 15,
      "row": 9
    },
    "106": {
      "col": 16,
      "row": 9
    },
    "107": {
      "col": 17,
      "row": 9
    },
    "108": {
      "col": 18,
      "row": 9
    },
    "109": {
      "col": 20,
      "row": 9
    },
    "110": {
      "col": 19,
      "row": 9
    },
    "111": {
      "col": 22,
      "row": 9
    },
    "112": {
      "col": 23,
      "row": 9
    },
    "113": {
      "col": 24,
      "row": 9
    },
    "114": {
      "col": 25,
      "row": 9
    },
    "115": {
      "col": 26,
      "row": 9
    },
    "116": {
      "col": 27,
      "row": 9
    },
    "117": {
      "col": 28,
      "row": 9
    },
    "118": {
      "col": 31,
      "row": 9
    },
    "119": {
      "col": 30,
      "row": 9
    },
    "120": {
      "col": 29,
      "row": 9
    },
    "121": {
      "col": 21,
      "row": 9
    },
    "122": {
      "col": 24,
      "row": 8
    },
    "123": {
      "col": 8,
      "row": 9
    },
    "124": {
      "col": 9,
      "row": 9
    },
    "125": {
      "col": 17,
      "row": 8
    },
    "126": {
      "col": 18,
      "row": 8
    },
    "127": {
      "col": 19,
      "row": 8
    },
    "128": {
      "col": 20,
      "row": 8
    },
    "129": {
      "col": 21,
      "row": 8
    },
    "130": {
      "col": 22,
      "row": 8
    },
    "131": {
      "col": 23,
      "row": 8
    },
    "132": {
      "col": 1,
      "row": 4
    },
    "133": {
      "col": 3,
      "row": 4
    },
    "134": {
      "col": 3,
      "row": 4
    },
    "135": {
      "col": 3,
      "row": 4
    },
    "136": {
      "col": 3,
      "row": 4
    },
    "137": {
      "col": 3,
      "row": 4
    },
    "138": {
      "col": 3,
      "row": 4
    },
    "139": {
      "col": 3,
      "row": 4
    },
    "140": {
      "col": 3,
      "row": 4
    },
    "141": {
      "col": 3,
      "row": 4
    },
    "142": {
      "col": 3,
      "row": 4
    },
    "143": {
      "col": 3,
      "row": 4
    },
    "144": {
      "col": 3,
      "row": 4
    },
    "145": {
      "col": 3,
      "row": 4
    },
    "146": {
      "col": 3,
      "row": 4
    },
    "147": {
      "col": 3,
      "row": 4
    },
    "148": {
      "col": 3,
      "row": 4
    },
    "149": {
      "col": 3,
      "row": 4
    },
    "150": {
      "col": 3,
      "row": 4
    },
    "151": {
      "col": 3,
      "row": 4
    },
    "152": {
      "col": 3,
      "row": 4
    },
    "153": {
      "col": 3,
      "row": 4
    },
    "154": {
      "col": 3,
      "row": 4
    },
    "155": {
      "col": 3,
      "row": 4
    },
    "156": {
      "col": 3,
      "row": 4
    },
    "157": {
      "col": 3,
      "row": 4
    },
    "158": {
      "col": 3,
      "row": 4
    },
    "159": {
      "col": 3,
      "row": 4
    },
    "160": {
      "col": 3,
      "row": 4
    },
    "161": {
      "col": 3,
      "row": 4
    },
    "162": {
      "col": 3,
      "row": 4
    },
    "163": {
      "col": 3,
      "row": 7
    },
    "164": {
      "col": 3,
      "row": 7
    },
    "165": {
      "col": 3,
      "row": 7
    },
    "166": {
      "col": 3,
      "row": 7
    },
    "167": {
      "col": 3,
      "row": 7
    },
    "168": {
      "col": 3,
      "row": 7
    },
    "169": {
      "col": 3,
      "row": 7
    },
    "171": {
      "col": 3,
      "row": 7
    },
    "172": {
      "col": 3,
      "row": 7
    },
    "173": {
      "col": 28,
      "row": 3
    },
    "174": {
      "col": 28,
      "row": 3
    },
    "175": {
      "col": 28,
      "row": 3
    },
    "176": {
      "col": 28,
      "row": 3
    },
    "177": {
      "col": 28,
      "row": 3
    },
    "178": {
      "col": 28,
      "row": 3
    },
    "179": {
      "col": 28,
      "row": 3
    },
    "180": {
      "col": 28,
      "row": 3
    },
    "181": {
      "col": 28,
      "row": 3
    },
    "182": {
      "col": 28,
      "row": 3
    },
    "183": {
      "col": 28,
      "row": 3
    },
    "184": {
      "col": 28,
      "row": 3
    },
    "185": {
      "col": 28,
      "row": 3
    },
    "186": {
      "col": 28,
      "row": 3
    },
    "187": {
      "col": 28,
      "row": 3
    },
    "188": {
      "col": 28,
      "row": 3
    },
    "189": {
      "col": 28,
      "row": 3
    },
    "190": {
      "col": 28,
      "row": 3
    },
    "191": {
      "col": 28,
      "row": 3
    },
    "192": {
      "col": 28,
      "row": 3
    },
    "193": {
      "col": 28,
      "row": 3
    },
    "194": {
      "col": 28,
      "row": 3
    },
    "195": {
      "col": 17,
      "row": 54
    },
    "196": {
      "col": 15,
      "row": 54
    },
    "197": {
      "col": 28,
      "row": 3
    },
    "198": {
      "col": 28,
      "row": 3
    },
    "199": {
      "col": 28,
      "row": 3
    },
    "200": {
      "col": 28,
      "row": 3
    },
    "201": {
      "col": 28,
      "row": 3
    },
    "202": {
      "col": 28,
      "row": 3
    },
    "203": {
      "col": 28,
      "row": 3
    },
    "204": {
      "col": 28,
      "row": 3
    },
    "205": {
      "col": 28,
      "row": 3
    },
    "206": {
      "col": 28,
      "row": 3
    },
    "207": {
      "col": 28,
      "row": 3
    },
    "208": {
      "col": 28,
      "row": 3
    },
    "209": {
      "col": 28,
      "row": 3
    },
    "210": {
      "col": 28,
      "row": 3
    },
    "211": {
      "col": 28,
      "row": 3
    },
    "212": {
      "col": 28,
      "row": 3
    },
    "213": {
      "col": 28,
      "row": 3
    },
    "214": {
      "col": 28,
      "row": 3
    },
    "215": {
      "col": 28,
      "row": 3
    },
    "216": {
      "col": 28,
      "row": 3
    },
    "217": {
      "col": 28,
      "row": 3
    },
    "218": {
      "col": 28,
      "row": 3
    },
    "219": {
      "col": 28,
      "row": 3
    },
    "220": {
      "col": 28,
      "row": 3
    },
    "221": {
      "col": 28,
      "row": 3
    },
    "222": {
      "col": 5,
      "row": 5
    },
    "223": {
      "col": 5,
      "row": 5
    },
    "224": {
      "col": 5,
      "row": 5
    },
    "225": {
      "col": 5,
      "row": 5
    },
    "226": {
      "col": 5,
      "row": 5
    },
    "227": {
      "col": 5,
      "row": 5
    },
    "228": {
      "col": 5,
      "row": 5
    },
    "229": {
      "col": 5,
      "row": 5
    },
    "230": {
      "col": 5,
      "row": 5
    },
    "231": {
      "col": 5,
      "row": 5
    },
    "232": {
      "col": 5,
      "row": 5
    },
    "233": {
      "col": 5,
      "row": 5
    },
    "234": {
      "col": 5,
      "row": 5
    },
    "235": {
      "col": 5,
      "row": 5
    },
    "236": {
      "col": 5,
      "row": 5
    },
    "237": {
      "col": 5,
      "row": 5
    },
    "238": {
      "col": 5,
      "row": 5
    },
    "239": {
      "col": 5,
      "row": 5
    },
    "240": {
      "col": 5,
      "row": 5
    },
    "241": {
      "col": 5,
      "row": 5
    },
    "242": {
      "col": 5,
      "row": 5
    },
    "243": {
      "col": 5,
      "row": 5
    },
    "244": {
      "col": 5,
      "row": 5
    },
    "245": {
      "col": 5,
      "row": 5
    },
    "246": {
      "col": 5,
      "row": 5
    },
    "247": {
      "col": 5,
      "row": 5
    },
    "248": {
      "col": 5,
      "row": 5
    },
    "249": {
      "col": 5,
      "row": 5
    },
    "250": {
      "col": 5,
      "row": 5
    },
    "251": {
      "col": 5,
      "row": 5
    },
    "252": {
      "col": 5,
      "row": 5
    },
    "253": {
      "col": 5,
      "row": 5
    },
    "254": {
      "col": 5,
      "row": 5
    },
    "255": {
      "col": 5,
      "row": 5
    },
    "256": {
      "col": 5,
      "row": 5
    },
    "257": {
      "col": 5,
      "row": 5
    },
    "258": {
      "col": 5,
      "row": 5
    },
    "259": {
      "col": 5,
      "row": 5
    },
    "260": {
      "col": 5,
      "row": 5
    },
    "261": {
      "col": 5,
      "row": 5
    },
    "262": {
      "col": 5,
      "row": 5
    },
    "263": {
      "col": 5,
      "row": 5
    },
    "264": {
      "col": 5,
      "row": 5
    },
    "265": {
      "col": 5,
      "row": 5
    },
    "266": {
      "col": 5,
      "row": 5
    },
    "267": {
      "col": 5,
      "row": 5
    },
    "268": {
      "col": 5,
      "row": 5
    },
    "269": {
      "col": 19,
      "row": 6
    },
    "270": {
      "col": 19,
      "row": 6
    },
    "271": {
      "col": 19,
      "row": 6
    },
    "272": {
      "col": 19,
      "row": 6
    },
    "273": {
      "col": 19,
      "row": 6
    },
    "274": {
      "col": 19,
      "row": 6
    },
    "275": {
      "col": 19,
      "row": 6
    },
    "276": {
      "col": 19,
      "row": 6
    },
    "277": {
      "col": 19,
      "row": 6
    },
    "278": {
      "col": 19,
      "row": 6
    },
    "279": {
      "col": 19,
      "row": 6
    },
    "280": {
      "col": 19,
      "row": 6
    },
    "281": {
      "col": 19,
      "row": 6
    },
    "282": {
      "col": 19,
      "row": 6
    },
    "283": {
      "col": 19,
      "row": 6
    },
    "284": {
      "col": 19,
      "row": 6
    },
    "285": {
      "col": 19,
      "row": 6
    },
    "286": {
      "col": 19,
      "row": 6
    },
    "287": {
      "col": 19,
      "row": 6
    },
    "288": {
      "col": 19,
      "row": 6
    },
    "289": {
      "col": 19,
      "row": 6
    },
    "290": {
      "col": 19,
      "row": 6
    },
    "291": {
      "col": 19,
      "row": 6
    },
    "292": {
      "col": 19,
      "row": 6
    },
    "293": {
      "col": 16,
      "row": 54
    },
    "294": {
      "col": 19,
      "row": 6
    },
    "295": {
      "col": 19,
      "row": 6
    },
    "296": {
      "col": 19,
      "row": 6
    },
    "297": {
      "col": 19,
      "row": 6
    },
    "298": {
      "col": 19,
      "row": 6
    },
    "299": {
      "col": 19,
      "row": 6
    },
    "300": {
      "col": 18,
      "row": 7
    },
    "301": {
      "col": 18,
      "row": 7
    },
    "302": {
      "col": 18,
      "row": 7
    },
    "303": {
      "col": 18,
      "row": 7
    },
    "304": {
      "col": 18,
      "row": 7
    },
    "305": {
      "col": 18,
      "row": 7
    },
    "306": {
      "col": 18,
      "row": 7
    },
    "307": {
      "col": 18,
      "row": 7
    },
    "308": {
      "col": 18,
      "row": 7
    },
    "309": {
      "col": 18,
      "row": 7
    },
    "310": {
      "col": 18,
      "row": 7
    },
    "311": {
      "col": 18,
      "row": 7
    },
    "312": {
      "col": 18,
      "row": 7
    },
    "313": {
      "col": 18,
      "row": 7
    },
    "314": {
      "col": 18,
      "row": 7
    },
    "315": {
      "col": 18,
      "row": 7
    },
    "316": {
      "col": 18,
      "row": 7
    },
    "317": {
      "col": 18,
      "row": 7
    },
    "318": {
      "col": 18,
      "row": 7
    },
    "319": {
      "col": 18,
      "row": 7
    },
    "320": {
      "col": 18,
      "row": 7
    },
    "321": {
      "col": 18,
      "row": 7
    },
    "322": {
      "col": 18,
      "row": 7
    },
    "323": {
      "col": 18,
      "row": 7
    },
    "324": {
      "col": 18,
      "row": 7
    },
    "325": {
      "col": 18,
      "row": 7
    },
    "326": {
      "col": 18,
      "row": 7
    },
    "327": {
      "col": 18,
      "row": 7
    },
    "328": {
      "col": 18,
      "row": 7
    },
    "329": {
      "col": 18,
      "row": 7
    },
    "330": {
      "col": 4,
      "row": 13
    },
    "331": {
      "col": 5,
      "row": 13
    },
    "332": {
      "col": 6,
      "row": 13
    },
    "333": {
      "col": 7,
      "row": 13
    },
    "334": {
      "col": 28,
      "row": 12
    },
    "335": {
      "col": 29,
      "row": 12
    },
    "336": {
      "col": 30,
      "row": 12
    },
    "337": {
      "col": 31,
      "row": 12
    },
    "338": {
      "col": 25,
      "row": 4
    },
    "339": {
      "col": 26,
      "row": 4
    },
    "340": {
      "col": 27,
      "row": 4
    },
    "341": {
      "col": 28,
      "row": 4
    },
    "342": {
      "col": 29,
      "row": 4
    },
    "343": {
      "col": 30,
      "row": 4
    },
    "344": {
      "col": 31,
      "row": 4
    },
    "345": {
      "col": 9,
      "row": 14
    },
    "346": {
      "col": 11,
      "row": 14
    },
    "347": {
      "col": 10,
      "row": 14
    },
    "348": {
      "col": 8,
      "row": 14
    },
    "349": {
      "col": 7,
      "row": 14
    },
    "350": {
      "col": 3,
      "row": 6
    },
    "351": {
      "col": 3,
      "row": 6
    },
    "352": {
      "col": 3,
      "row": 6
    },
    "353": {
      "col": 3,
      "row": 6
    },
    "354": {
      "col": 3,
      "row": 6
    },
    "355": {
      "col": 3,
      "row": 6
    },
    "356": {
      "col": 3,
      "row": 6
    },
    "357": {
      "col": 3,
      "row": 6
    },
    "358": {
      "col": 3,
      "row": 6
    },
    "359": {
      "col": 3,
      "row": 6
    },
    "360": {
      "col": 3,
      "row": 6
    },
    "361": {
      "col": 3,
      "row": 6
    },
    "362": {
      "col": 3,
      "row": 6
    },
    "363": {
      "col": 3,
      "row": 6
    },
    "364": {
      "col": 3,
      "row": 6
    },
    "365": {
      "col": 3,
      "row": 6
    },
    "366": {
      "col": 3,
      "row": 6
    },
    "367": {
      "col": 3,
      "row": 6
    },
    "368": {
      "col": 3,
      "row": 6
    },
    "369": {
      "col": 3,
      "row": 6
    },
    "370": {
      "col": 3,
      "row": 6
    },
    "371": {
      "col": 3,
      "row": 6
    },
    "372": {
      "col": 3,
      "row": 6
    },
    "373": {
      "col": 3,
      "row": 6
    },
    "374": {
      "col": 3,
      "row": 6
    },
    "375": {
      "col": 3,
      "row": 6
    },
    "376": {
      "col": 3,
      "row": 6
    },
    "377": {
      "col": 3,
      "row": 6
    },
    "379": {
      "col": 0,
      "row": 13
    },
    "380": {
      "col": 1,
      "row": 13
    },
    "381": {
      "col": 2,
      "row": 13
    },
    "382": {
      "col": 3,
      "row": 13
    },
    "383": {
      "col": 24,
      "row": 12
    },
    "384": {
      "col": 25,
      "row": 12
    },
    "385": {
      "col": 26,
      "row": 12
    },
    "386": {
      "col": 27,
      "row": 12
    },
    "387": {
      "col": 8,
      "row": 13
    },
    "388": {
      "col": 9,
      "row": 13
    },
    "389": {
      "col": 18,
      "row": 14
    },
    "390": {
      "col": 19,
      "row": 14
    },
    "391": {
      "col": 20,
      "row": 14
    },
    "392": {
      "col": 21,
      "row": 14
    },
    "393": {
      "col": 26,
      "row": 14
    },
    "394": {
      "col": 27,
      "row": 14
    },
    "395": {
      "col": 22,
      "row": 14
    },
    "396": {
      "col": 24,
      "row": 14
    },
    "397": {
      "col": 23,
      "row": 14
    },
    "398": {
      "col": 25,
      "row": 14
    },
    "399": {
      "col": 10,
      "row": 53
    },
    "400": {
      "col": 2,
      "row": 10
    },
    "401": {
      "col": 0,
      "row": 10
    },
    "402": {
      "col": 1,
      "row": 10
    },
    "403": {
      "col": 3,
      "row": 10
    },
    "404": {
      "col": 4,
      "row": 10
    },
    "405": {
      "col": 11,
      "row": 10
    },
    "406": {
      "col": 7,
      "row": 10
    },
    "407": {
      "col": 9,
      "row": 10
    },
    "408": {
      "col": 5,
      "row": 10
    },
    "409": {
      "col": 6,
      "row": 10
    },
    "410": {
      "col": 8,
      "row": 10
    },
    "411": {
      "col": 10,
      "row": 10
    },
    "412": {
      "col": 12,
      "row": 10
    },
    "413": {
      "col": 2,
      "row": 8
    },
    "414": {
      "col": 28,
      "row": 8
    },
    "415": {
      "col": 5,
      "row": 5
    },
    "416": {
      "col": 5,
      "row": 5
    },
    "417": {
      "col": 5,
      "row": 5
    },
    "418": {
      "col": 5,
      "row": 5
    },
    "419": {
      "col": 5,
      "row": 5
    },
    "420": {
      "col": 5,
      "row": 5
    },
    "421": {
      "col": 5,
      "row": 5
    },
    "422": {
      "col": 5,
      "row": 5
    },
    "423": {
      "col": 10,
      "row": 13
    },
    "424": {
      "col": 11,
      "row": 13
    },
    "425": {
      "col": 3,
      "row": 4
    },
    "426": {
      "col": 3,
      "row": 4
    },
    "427": {
      "col": 3,
      "row": 4
    },
    "428": {
      "col": 3,
      "row": 4
    },
    "429": {
      "col": 3,
      "row": 4
    },
    "430": {
      "col": 3,
      "row": 4
    },
    "431": {
      "col": 3,
      "row": 4
    },
    "432": {
      "col": 3,
      "row": 4
    },
    "433": {
      "col": 3,
      "row": 4
    },
    "434": {
      "col": 3,
      "row": 4
    },
    "435": {
      "col": 3,
      "row": 4
    },
    "436": {
      "col": 3,
      "row": 4
    },
    "437": {
      "col": 5,
      "row": 5
    },
    "438": {
      "col": 5,
      "row": 5
    },
    "439": {
      "col": 5,
      "row": 5
    },
    "480": {
      "col": 17,
      "row": 3
    },
    "481": {
      "col": 17,
      "row": 3
    },
    "482": {
      "col": 17,
      "row": 3
    },
    "483": {
      "col": 18,
      "row": 3
    },
    "484": {
      "col": 18,
      "row": 3
    },
    "485": {
      "col": 18,
      "row": 3
    },
    "486": {
      "col": 22,
      "row": 3
    },
    "487": {
      "col": 22,
      "row": 3
    },
    "488": {
      "col": 19,
      "row": 3
    },
    "489": {
      "col": 19,
      "row": 3
    },
    "490": {
      "col": 19,
      "row": 3
    },
    "491": {
      "col": 23,
      "row": 3
    },
    "492": {
      "col": 24,
      "row": 3
    },
    "493": {
      "col": 25,
      "row": 3
    },
    "494": {
      "col": 26,
      "row": 3
    },
    "495": {
      "col": 27,
      "row": 3
    },
    "496": {
      "col": 20,
      "row": 3
    },
    "497": {
      "col": 21,
      "row": 3
    },
    "498": {
      "col": 30,
      "row": 8
    },
    "499": {
      "col": 30,
      "row": 11
    },
    "500": {
      "col": 29,
      "row": 14
    },
    "501": {
      "col": 30,
      "row": 14
    },
    "502": {
      "col": 31,
      "row": 14
    },
    "503": {
      "col": 22,
      "row": 4
    },
    "504": {
      "col": 23,
      "row": 4
    },
    "505": {
      "col": 24,
      "row": 4
    },
    "506": {
      "col": 15,
      "row": 4
    },
    "507": {
      "col": 16,
      "row": 4
    },
    "508": {
      "col": 18,
      "row": 4
    },
    "509": {
      "col": 19,
      "row": 4
    },
    "510": {
      "col": 20,
      "row": 4
    },
    "511": {
      "col": 21,
      "row": 4
    },
    "512": {
      "col": 16,
      "row": 13
    },
    "513": {
      "col": 17,
      "row": 13
    },
    "514": {
      "col": 18,
      "row": 13
    },
    "515": {
      "col": 19,
      "row": 13
    },
    "516": {
      "col": 12,
      "row": 13
    },
    "517": {
      "col": 13,
      "row": 13
    },
    "518": {
      "col": 14,
      "row": 13
    },
    "519": {
      "col": 15,
      "row": 13
    },
    "520": {
      "col": 3,
      "row": 7
    },
    "521": {
      "col": 3,
      "row": 7
    },
    "522": {
      "col": 3,
      "row": 7
    },
    "523": {
      "col": 3,
      "row": 7
    },
    "524": {
      "col": 12,
      "row": 53
    },
    "525": {
      "col": 1,
      "row": 53
    },
    "526": {
      "col": 18,
      "row": 54
    },
    "527": {
      "col": 2,
      "row": 54
    },
    "528": {
      "col": 5,
      "row": 53
    },
    "529": {
      "col": 0,
      "row": 53
    },
    "530": {
      "col": 3,
      "row": 54
    },
    "531": {
      "col": 12,
      "row": 54
    },
    "532": {
      "col": 6,
      "row": 53
    },
    "533": {
      "col": 15,
      "row": 53
    },
    "535": {
      "col": 8,
      "row": 54
    },
    "536": {
      "col": 0,
      "row": 54
    },
    "537": {
      "col": 16,
      "row": 53
    },
    "538": {
      "col": 7,
      "row": 53
    },
    "539": {
      "col": 17,
      "row": 53
    },
    "540": {
      "col": 19,
      "row": 53
    },
    "541": {
      "col": 18,
      "row": 53
    },
    "542": {
      "col": 20,
      "row": 53
    },
    "543": {
      "col": 4,
      "row": 53
    },
    "544": {
      "col": 20,
      "row": 53
    },
    "545": {
      "col": 3,
      "row": 53
    },
    "546": {
      "col": 13,
      "row": 53
    },
    "547": {
      "col": 14,
      "row": 53
    },
    "548": {
      "col": 11,
      "row": 53
    },
    "549": {
      "col": 24,
      "row": 53
    },
    "550": {
      "col": 8,
      "row": 53
    },
    "551": {
      "col": 21,
      "row": 53
    },
    "552": {
      "col": 22,
      "row": 53
    },
    "553": {
      "col": 2,
      "row": 53
    },
    "554": {
      "col": 25,
      "row": 53
    },
    "555": {
      "col": 23,
      "row": 53
    },
    "556": {
      "col": 19,
      "row": 54
    },
    "557": {
      "col": 11,
      "row": 54
    },
    "558": {
      "col": 10,
      "row": 54
    },
    "559": {
      "col": 9,
      "row": 54
    },
    "560": {
      "col": 4,
      "row": 54
    },
    "561": {
      "col": 13,
      "row": 54
    },
    "562": {
      "col": 5,
      "row": 54
    },
    "563": {
      "col": 1,
      "row": 54
    },
    "564": {
      "col": 30,
      "row": 13
    },
    "565": {
      "col": 27,
      "row": 53
    },
    "566": {
      "col": 28,
      "row": 3
    },
    "567": {
      "col": 6,
      "row": 63
    },
    "568": {
      "col": 7,
      "row": 63
    },
    "569": {
      "col": 8,
      "row": 63
    },
    "570": {
      "col": 9,
      "row": 63
    },
    "571": {
      "col": 10,
      "row": 63
    },
    "572": {
      "col": 11,
      "row": 63
    },
    "573": {
      "col": 12,
      "row": 63
    },
    "574": {
      "col": 13,
      "row": 63
    },
    "575": {
      "col": 14,
      "row": 63
    },
    "576": {
      "col": 15,
      "row": 63
    },
    "577": {
      "col": 16,
      "row": 63
    },
    "580": {
      "col": 29,
      "row": 11
    },
    "581": {
      "col": 14,
      "row": 54
    },
    "590": {
      "col": 28,
      "row": 53
    }
  },
  "spells": {
    "48": {
      "col": 8,
      "row": 17
    },
    "49": {
      "col": 9,
      "row": 17
    },
    "50": {
      "col": 10,
      "row": 17
    },
    "51": {
      "col": 11,
      "row": 17
    },
    "52": {
      "col": 12,
      "row": 17
    },
    "53": {
      "col": 13,
      "row": 17
    },
    "54": {
      "col": 14,
      "row": 17
    },
    "55": {
      "col": 15,
      "row": 17
    },
    "56": {
      "col": 16,
      "row": 17
    },
    "57": {
      "col": 17,
      "row": 17
    },
    "58": {
      "col": 18,
      "row": 17
    },
    "59": {
      "col": 19,
      "row": 17
    },
    "60": {
      "col": 20,
      "row": 17
    },
    "61": {
      "col": 21,
      "row": 17
    },
    "62": {
      "col": 22,
      "row": 17
    },
    "63": {
      "col": 23,
      "row": 17
    },
    "64": {
      "col": 0,
      "row": 15
    },
    "65": {
      "col": 4,
      "row": 15
    },
    "66": {
      "col": 8,
      "row": 15
    },
    "67": {
      "col": 12,
      "row": 15
    },
    "68": {
      "col": 16,
      "row": 15
    },
    "69": {
      "col": 20,
      "row": 15
    },
    "70": {
      "col": 24,
      "row": 15
    },
    "71": {
      "col": 28,
      "row": 15
    },
    "72": {
      "col": 0,
      "row": 16
    },
    "73": {
      "col": 4,
      "row": 16
    },
    "74": {
      "col": 8,
      "row": 16
    },
    "75": {
      "col": 12,
      "row": 16
    },
    "76": {
      "col": 16,
      "row": 16
    },
    "77": {
      "col": 20,
      "row": 16
    },
    "78": {
      "col": 24,
      "row": 16
    },
    "79": {
      "col": 28,
      "row": 16
    },
    "80": {
      "col": 1,
      "row": 15
    },
    "81": {
      "col": 5,
      "row": 15
    },
    "82": {
      "col": 9,
      "row": 15
    },
    "83": {
      "col": 13,
      "row": 15
    },
    "84": {
      "col": 17,
      "row": 15
    },
    "85": {
      "col": 21,
      "row": 15
    },
    "86": {
      "col": 25,
      "row": 15
    },
    "87": {
      "col": 29,
      "row": 15
    },
    "88": {
      "col": 1,
      "row": 16
    },
    "89": {
      "col": 5,
      "row": 16
    },
    "90": {
      "col": 9,
      "row": 16
    },
    "91": {
      "col": 13,
      "row": 16
    },
    "92": {
      "col": 17,
      "row": 16
    },
    "93": {
      "col": 21,
      "row": 16
    },
    "94": {
      "col": 25,
      "row": 16
    },
    "95": {
      "col": 29,
      "row": 16
    },
    "96": {
      "col": 2,
      "row": 15
    },
    "97": {
      "col": 6,
      "row": 15
    },
    "98": {
      "col": 10,
      "row": 15
    },
    "99": {
      "col": 14,
      "row": 15
    },
    "100": {
      "col": 18,
      "row": 15
    },
    "101": {
      "col": 22,
      "row": 15
    },
    "102": {
      "col": 26,
      "row": 15
    },
    "103": {
      "col": 30,
      "row": 15
    },
    "104": {
      "col": 2,
      "row": 16
    },
    "105": {
      "col": 6,
      "row": 16
    },
    "106": {
      "col": 10,
      "row": 16
    },
    "107": {
      "col": 14,
      "row": 16
    },
    "108": {
      "col": 18,
      "row": 16
    },
    "109": {
      "col": 22,
      "row": 16
    },
    "110": {
      "col": 26,
      "row": 16
    },
    "111": {
      "col": 30,
      "row": 16
    },
    "112": {
      "col": 3,
      "row": 15
    },
    "113": {
      "col": 7,
      "row": 15
    },
    "114": {
      "col": 11,
      "row": 15
    },
    "115": {
      "col": 15,
      "row": 15
    },
    "116": {
      "col": 19,
      "row": 15
    },
    "117": {
      "col": 23,
      "row": 15
    },
    "118": {
      "col": 27,
      "row": 15
    },
    "119": {
      "col": 31,
      "row": 15
    },
    "120": {
      "col": 3,
      "row": 16
    },
    "121": {
      "col": 7,
      "row": 16
    },
    "122": {
      "col": 11,
      "row": 16
    },
    "123": {
      "col": 15,
      "row": 16
    },
    "124": {
      "col": 19,
      "row": 16
    },
    "125": {
      "col": 23,
      "row": 16
    },
    "126": {
      "col": 27,
      "row": 16
    },
    "127": {
      "col": 31,
      "row": 16
    },
    "128": {
      "col": 7,
      "row": 7
    },
    "129": {
      "col": 0,
      "row": 7
    },
    "130": {
      "col": 8,
      "row": 7
    },
    "131": {
      "col": 2,
      "row": 7
    },
    "132": {
      "col": 3,
      "row": 7
    },
    "133": {
      "col": 4,
      "row": 7
    },
    "134": {
      "col": 5,
      "row": 7
    },
    "135": {
      "col": 6,
      "row": 7
    },
    "136": {
      "col": 1,
      "row": 7
    },
    "137": {
      "col": 1,
      "row": 7
    },
    "138": {
      "col": 9,
      "row": 7
    },
    "139": {
      "col": 10,
      "row": 7
    },
    "140": {
      "col": 11,
      "row": 7
    },
    "141": {
      "col": 12,
      "row": 7
    },
    "142": {
      "col": 13,
      "row": 7
    },
    "143": {
      "col": 14,
      "row": 7
    },
    "144": {
      "col": 7,
      "row": 4
    },
    "145": {
      "col": 0,
      "row": 4
    },
    "146": {
      "col": 8,
      "row": 4
    },
    "147": {
      "col": 2,
      "row": 4
    },
    "148": {
      "col": 3,
      "row": 4
    },
    "149": {
      "col": 4,
      "row": 4
    },
    "150": {
      "col": 5,
      "row": 4
    },
    "151": {
      "col": 6,
      "row": 4
    },
    "152": {
      "col": 1,
      "row": 4
    },
    "153": {
      "col": 1,
      "row": 4
    },
    "154": {
      "col": 9,
      "row": 4
    },
    "155": {
      "col": 10,
      "row": 4
    },
    "156": {
      "col": 11,
      "row": 4
    },
    "157": {
      "col": 12,
      "row": 4
    },
    "158": {
      "col": 13,
      "row": 4
    },
    "159": {
      "col": 14,
      "row": 4
    },
    "160": {
      "col": 22,
      "row": 7
    },
    "161": {
      "col": 21,
      "row": 7
    },
    "162": {
      "col": 21,
      "row": 7
    },
    "163": {
      "col": 18,
      "row": 7
    },
    "164": {
      "col": 18,
      "row": 7
    },
    "165": {
      "col": 19,
      "row": 7
    },
    "166": {
      "col": 21,
      "row": 7
    },
    "167": {
      "col": 16,
      "row": 7
    },
    "168": {
      "col": 21,
      "row": 7
    },
    "169": {
      "col": 21,
      "row": 7
    },
    "170": {
      "col": 18,
      "row": 7
    },
    "171": {
      "col": 20,
      "row": 7
    },
    "172": {
      "col": 18,
      "row": 7
    },
    "173": {
      "col": 19,
      "row": 7
    },
    "174": {
      "col": 22,
      "row": 7
    },
    "175": {
      "col": 16,
      "row": 7
    },
    "176": {
      "col": 23,
      "row": 6
    },
    "177": {
      "col": 16,
      "row": 6
    },
    "178": {
      "col": 24,
      "row": 6
    },
    "179": {
      "col": 18,
      "row": 6
    },
    "180": {
      "col": 19,
      "row": 6
    },
    "181": {
      "col": 20,
      "row": 6
    },
    "182": {
      "col": 21,
      "row": 6
    },
    "183": {
      "col": 22,
      "row": 6
    },
    "184": {
      "col": 17,
      "row": 6
    },
    "185": {
      "col": 17,
      "row": 6
    },
    "186": {
      "col": 25,
      "row": 6
    },
    "187": {
      "col": 26,
      "row": 6
    },
    "188": {
      "col": 27,
      "row": 6
    },
    "189": {
      "col": 28,
      "row": 6
    },
    "190": {
      "col": 29,
      "row": 6
    },
    "191": {
      "col": 30,
      "row": 6
    },
    "192": {
      "col": 7,
      "row": 6
    },
    "193": {
      "col": 0,
      "row": 6
    },
    "194": {
      "col": 8,
      "row": 6
    },
    "195": {
      "col": 2,
      "row": 6
    },
    "196": {
      "col": 3,
      "row": 6
    },
    "197": {
      "col": 4,
      "row": 6
    },
    "198": {
      "col": 5,
      "row": 6
    },
    "199": {
      "col": 6,
      "row": 6
    },
    "200": {
      "col": 1,
      "row": 6
    },
    "201": {
      "col": 1,
      "row": 6
    },
    "202": {
      "col": 9,
      "row": 6
    },
    "203": {
      "col": 10,
      "row": 6
    },
    "204": {
      "col": 11,
      "row": 6
    },
    "205": {
      "col": 12,
      "row": 6
    },
    "206": {
      "col": 13,
      "row": 6
    },
    "207": {
      "col": 14,
      "row": 6
    },
    "208": {
      "col": 28,
      "row": 3
    },
    "209": {
      "col": 29,
      "row": 3
    },
    "210": {
      "col": 30,
      "row": 3
    },
    "211": {
      "col": 31,
      "row": 3
    },
    "212": {
      "col": 28,
      "row": 3
    },
    "213": {
      "col": 29,
      "row": 3
    },
    "214": {
      "col": 30,
      "row": 3
    },
    "215": {
      "col": 31,
      "row": 3
    },
    "216": {
      "col": 28,
      "row": 3
    },
    "217": {
      "col": 29,
      "row": 3
    },
    "218": {
      "col": 30,
      "row": 3
    },
    "219": {
      "col": 31,
      "row": 3
    },
    "220": {
      "col": 28,
      "row": 3
    },
    "221": {
      "col": 29,
      "row": 3
    },
    "222": {
      "col": 30,
      "row": 3
    },
    "223": {
      "col": 31,
      "row": 3
    },
    "224": {
      "col": 7,
      "row": 5
    },
    "225": {
      "col": 0,
      "row": 5
    },
    "226": {
      "col": 8,
      "row": 5
    },
    "227": {
      "col": 2,
      "row": 5
    },
    "228": {
      "col": 3,
      "row": 5
    },
    "229": {
      "col": 4,
      "row": 5
    },
    "230": {
      "col": 5,
      "row": 5
    },
    "231": {
      "col": 6,
      "row": 5
    },
    "232": {
      "col": 1,
      "row": 5
    },
    "233": {
      "col": 1,
      "row": 5
    },
    "234": {
      "col": 9,
      "row": 5
    },
    "235": {
      "col": 10,
      "row": 5
    },
    "236": {
      "col": 11,
      "row": 5
    },
    "237": {
      "col": 12,
      "row": 5
    },
    "238": {
      "col": 13,
      "row": 5
    },
    "239": {
      "col": 14,
      "row": 5
    },
    "240": {
      "col": 23,
      "row": 5
    },
    "241": {
      "col": 16,
      "row": 5
    },
    "242": {
      "col": 24,
      "row": 5
    },
    "243": {
      "col": 18,
      "row": 5
    },
    "244": {
      "col": 19,
      "row": 5
    },
    "245": {
      "col": 20,
      "row": 5
    },
    "246": {
      "col": 21,
      "row": 5
    },
    "247": {
      "col": 22,
      "row": 5
    },
    "248": {
      "col": 17,
      "row": 5
    },
    "249": {
      "col": 17,
      "row": 5
    },
    "250": {
      "col": 25,
      "row": 5
    },
    "251": {
      "col": 26,
      "row": 5
    },
    "252": {
      "col": 27,
      "row": 5
    },
    "253": {
      "col": 28,
      "row": 5
    },
    "254": {
      "col": 29,
      "row": 5
    },
    "255": {
      "col": 30,
      "row": 5
    }
  },
  "player": {
    "col": 0,
    "row": 18
  }
}